sphinxcontrib_sqlalchemyviz-0.3-nspkg.pth
sphinxcontrib/sqlalchemyviz.py
sphinxcontrib_sqlalchemyviz-0.3.dist-info/DESCRIPTION.rst
sphinxcontrib_sqlalchemyviz-0.3.dist-info/METADATA
sphinxcontrib_sqlalchemyviz-0.3.dist-info/RECORD
sphinxcontrib_sqlalchemyviz-0.3.dist-info/WHEEL
sphinxcontrib_sqlalchemyviz-0.3.dist-info/metadata.json
sphinxcontrib_sqlalchemyviz-0.3.dist-info/namespace_packages.txt
sphinxcontrib_sqlalchemyviz-0.3.dist-info/pbr.json
sphinxcontrib_sqlalchemyviz-0.3.dist-info/top_level.txt
