Metadata-Version: 2.0
Name: sphinxcontrib-sqlalchemyviz
Version: 0.3
Summary: Sphinx SQLAlchemyViz extension
Home-page: https://github.com/chintal/sphinxcontrib-sqlalchemyviz
Author: Chintalagiri Shashank
Author-email: shashank@chintal.in
License: BSD
Download-URL: https://github.com/chintal/sphinxcontrib-sqlalchemyviz
Platform: UNKNOWN
Classifier: Development Status :: 4 - Beta
Classifier: Environment :: Console
Classifier: Environment :: Web Environment
Classifier: Intended Audience :: Developers
Classifier: License :: OSI Approved :: BSD License
Classifier: Operating System :: POSIX :: Linux
Classifier: Programming Language :: Python
Classifier: Framework :: Sphinx :: Extension
Classifier: Topic :: Documentation
Classifier: Topic :: Utilities
Requires-Dist: SQLAlchemyViz
Requires-Dist: Sphinx (>=0.6)
